lapsus/__init__.py
lapsus-0.0.0.dist-info/LICENSE
lapsus-0.0.0.dist-info/METADATA
lapsus-0.0.0.dist-info/WHEEL
lapsus-0.0.0.dist-info/top_level.txt
lapsus-0.0.0.dist-info/RECORD
