Metadata-Version: 2.1
Name: lapsus
Version: 0.0.0
Summary: Shell history cleaner
Author-email: Andrea Blengino <ing.andrea.blengino@protonmail.com>
Maintainer-email: Andrea Blengino <ing.andrea.blengino@protonmail.com>
License: GNU GENERAL PUBLIC LICENSE
Project-URL: Homepage, https://github.com/AndreaBlengino/lapsus
Project-URL: Issues, https://github.com/AndreaBlengino/lapsus/issues
Project-URL: Repository, https://github.com/AndreaBlengino/lapsus
Classifier: Development Status :: 1 - Planning
Classifier: Environment :: Console
Classifier: Intended Audience :: End Users/Desktop
Classifier: Operating System :: POSIX :: Linux
Classifier: Operating System :: MacOS
Classifier: Programming Language :: Python
Classifier: Programming Language :: Python :: 3.12
Classifier: Topic :: System :: Shells
Requires-Python: >=3.12
License-File: LICENSE
